percentize/__init__.py
percentize/core.py
percentize-0.1.0.dist-info/licenses/LICENSE
percentize-0.1.0.dist-info/WHEEL
percentize-0.1.0.dist-info/METADATA
percentize-0.1.0.dist-info/RECORD
