Metadata-Version: 2.4
Name: percentize
Version: 0.1.0
Summary: Makes percentages from inputs
Author-email: oculine <disrupt73@gmail.com>
License-File: LICENSE
